mgraph_db/__init__.py
mgraph_db/mgraph/MGraph.py
mgraph_db/mgraph/__init__.py
mgraph_db/mgraph/actions/MGraph__Builder.py
mgraph_db/mgraph/actions/MGraph__Data.py
mgraph_db/mgraph/actions/MGraph__Defaults.py
mgraph_db/mgraph/actions/MGraph__Diff.py
mgraph_db/mgraph/actions/MGraph__Diff__Values.py
mgraph_db/mgraph/actions/MGraph__Edit.py
mgraph_db/mgraph/actions/MGraph__Export.py
mgraph_db/mgraph/actions/MGraph__Screenshot.py
mgraph_db/mgraph/actions/MGraph__Type__Resolver.py
mgraph_db/mgraph/actions/MGraph__Values.py
mgraph_db/mgraph/actions/__init__.py
mgraph_db/mgraph/actions/exporters/MGraph__Export__Base.py
mgraph_db/mgraph/actions/exporters/MGraph__Export__Cytoscape.py
mgraph_db/mgraph/actions/exporters/Model__Cytoscape__Types.py
mgraph_db/mgraph/actions/exporters/__init__.py
mgraph_db/mgraph/actions/exporters/dot/MGraph__Export__Dot.py
mgraph_db/mgraph/actions/exporters/dot/__init__.py
mgraph_db/mgraph/actions/exporters/dot/models/MGraph__Export__Dot__Config.py
mgraph_db/mgraph/actions/exporters/dot/models/MGraph__Export__Dot__Config__Display.py
mgraph_db/mgraph/actions/exporters/dot/models/MGraph__Export__Dot__Config__Edge.py
mgraph_db/mgraph/actions/exporters/dot/models/MGraph__Export__Dot__Config__Font.py
mgraph_db/mgraph/actions/exporters/dot/models/MGraph__Export__Dot__Config__Graph.py
mgraph_db/mgraph/actions/exporters/dot/models/MGraph__Export__Dot__Config__Node.py
mgraph_db/mgraph/actions/exporters/dot/models/MGraph__Export__Dot__Config__Render.py
mgraph_db/mgraph/actions/exporters/dot/models/MGraph__Export__Dot__Config__Shape.py
mgraph_db/mgraph/actions/exporters/dot/models/MGraph__Export__Dot__Config__Style.py
mgraph_db/mgraph/actions/exporters/dot/models/MGraph__Export__Dot__Config__Type.py
mgraph_db/mgraph/actions/exporters/dot/models/MGraph__Export__Dot__Config__Type__Node.py
mgraph_db/mgraph/actions/exporters/dot/models/MGraph__Export__Dot__Layout__Engine.py
mgraph_db/mgraph/actions/exporters/dot/models/__init__.py
mgraph_db-1.18.0.dist-info/LICENSE
mgraph_db-1.18.0.dist-info/METADATA
mgraph_db-1.18.0.dist-info/WHEEL
mgraph_db-1.18.0.dist-info/RECORD
