Metadata-Version: 2.1
Name: mgraph_db
Version: 1.18.0
Summary: MGraph-DB
Home-page: https://github.com/owasp-sbot/MGraph-DB
License: Apache 2.0
Author: Dinis Cruz
Author-email: dinis.cruz@owasp.org
Requires-Python: >=3.11,<4.0
Classifier: License :: Other/Proprietary License
Classifier: Programming Language :: Python :: 3
Classifier: Programming Language :: Python :: 3.11
Classifier: Programming Language :: Python :: 3.12
Requires-Dist: osbot-utils
Project-URL: Repository, https://github.com/owasp-sbot/MGraph-DB
